[{
		"face": "img/user.jpg",
		"what": "Brunch this weekend?",
		"who": "Min Li Chan",
		"notes": " I'll be in your neighborhood doing errands"
	},
	{
		"face": "img/user.jpg",
		"what": "You free this friday?",
		"who": "Jackie Chan",
		"notes": "You still have to treat me to dinner"
	},
	{
		"face": "img/user.jpg",
		"what": "Brunch this weekend?",
		"who": "Min Li Chan",
		"notes": " I'll be in your neighborhood doing errands"
	},
	{
		"face": "img/user.jpg",
		"what": "Brunch this weekend?",
		"who": "Min Li Chan",
		"notes": " I'll be in your neighborhood doing errands"
	},
	{
		"face": "img/user.jpg",
		"what": "Brunch this weekend?",
		"who": "Min Li Chan",
		"notes": " I'll be in your neighborhood doing errands"
	}
]